gfaaccesslib/__init__.py
gfaaccesslib/api.py
gfaaccesslib/api_exceptions.py
gfaaccesslib/api_helpers.py
gfaaccesslib/gfa.py
gfaaccesslib/logger.py
gfaaccesslib/comm/__init__.py
gfaaccesslib/comm/command.py
gfaaccesslib/comm/communication.py
gfaaccesslib/comm/errorpackage.py
gfaaccesslib/comm/gfasocket.py
gfaaccesslib/comm/header.py
gfaaccesslib/comm/logger.py
gfaaccesslib/modules/__init__.py
gfaaccesslib/modules/adccontroller.py
gfaaccesslib/modules/clockmanager.py
gfaaccesslib/modules/datamanager.py
gfaaccesslib/modules/exposecontroller.py
gfaaccesslib/modules/gfamodule.py
gfaaccesslib/modules/heartbeat.py
gfaaccesslib/modules/irqcontroller.py
gfaaccesslib/modules/logger.py
gfaaccesslib/modules/memorydump.py
gfaaccesslib/modules/pid.py
gfaaccesslib/modules/powercontroller.py
gfaaccesslib/modules/system_info.py
gfaaccesslib/modules/telemetry.py
gfaaccesslib/modules/test.py
gfaaccesslib/raws/__init__.py
gfaaccesslib/raws/e2v_ccd230_42.py
gfaaccesslib/raws/logger.py
gfaaccesslib/raws/rawdatamanager.py
gfaaccesslib-1.1.0.dist-info/METADATA
gfaaccesslib-1.1.0.dist-info/WHEEL
gfaaccesslib-1.1.0.dist-info/top_level.txt
gfaaccesslib-1.1.0.dist-info/RECORD
