Metadata-Version: 2.1
Name: gfaaccesslib
Version: 1.1.0
Summary: A library to access GFA devices
Home-page: UNKNOWN
Author: Otger Ballester
Author-email: otger@ifae.es
License: BSD
Platform: any
Classifier: Development Status :: 5 - Production/Stable
Classifier: Intended Audience :: Developers
Classifier: License :: OSI Approved :: BSD License
Classifier: Programming Language :: Python :: 3
Requires-Dist: numpy
Requires-Dist: Pillow
Requires-Dist: pytz
